gerby/__init__.py
gerby/application.py
gerby/configuration.py
gerby/database.py
gerby/delete-comment.py
gerby/static/logo.ico
gerby/static/logo.png
gerby/static/robots.txt
gerby/static/stacks.ico
gerby/static/css/bibliography.css
gerby/static/css/browse.css
gerby/static/css/comments.css
gerby/static/css/print.css
gerby/static/css/search.css
gerby/static/css/style.css
gerby/static/css/tag.css
gerby/static/css/toc.css
gerby/static/css/tree.css
gerby/static/images/alert.svg
gerby/static/images/bibliography.svg
gerby/static/images/blog.svg
gerby/static/images/clippy.svg
gerby/static/images/clock.svg
gerby/static/images/comments.svg
gerby/static/images/dependency.svg
gerby/static/images/diff.svg
gerby/static/images/email.svg
gerby/static/images/github.svg
gerby/static/images/graph.svg
gerby/static/images/icon.ams.png
gerby/static/images/icon.arxiv.png
gerby/static/images/icon.doi.png
gerby/static/images/icon.github.png
gerby/static/images/icon.pdf.png
gerby/static/images/icon.rss.png
gerby/static/images/info.svg
gerby/static/images/list-ordered.svg
gerby/static/images/minus.svg
gerby/static/images/plus.svg
gerby/static/images/preview-close.svg
gerby/static/images/preview-open.svg
gerby/static/images/search.svg
gerby/static/images/toc.svg
gerby/static/images/funding/columbia.jpg
gerby/static/images/funding/nsf.gif
gerby/static/images/funding/simons.png
gerby/static/js/comments.js
gerby/static/js/history.js
gerby/static/js/toggle.js
gerby/templates/bibliography.entry.html
gerby/templates/bibliography.notfound.html
gerby/templates/bibliography.overview.html
gerby/templates/comment.invalid-captcha.html
gerby/templates/comment.invalid-email.html
gerby/templates/comments.html
gerby/templates/comments.xml
gerby/templates/index.html
gerby/templates/layout.html
gerby/templates/macros.html
gerby/templates/search.html
gerby/templates/search.malformed.html
gerby/templates/tag.chapter.notfound.html
gerby/templates/tag.chapter.redirect.html
gerby/templates/tag.citation.html
gmt_gerby-0.1.5.dist-info/LICENSE
gmt_gerby-0.1.5.dist-info/METADATA
gmt_gerby-0.1.5.dist-info/WHEEL
gmt_gerby-0.1.5.dist-info/top_level.txt
gmt_gerby-0.1.5.dist-info/RECORD
